setup.py
verkkofillet/__init__.py
verkkofillet/__main__.py
verkkofillet/__msettings.py
verkkofillet/_default_func.py
verkkofillet/_run_shell.py
verkkofillet/bin/insert_aln_gaps.py
verkkofillet/plotting/__init__.py
verkkofillet/plotting/_baseQC.py
verkkofillet/plotting/_chr_mashmap.py
verkkofillet/preprocessing/__init__.py
verkkofillet/preprocessing/_chrNaming.py
verkkofillet/preprocessing/_estLoop.py
verkkofillet/preprocessing/_fill_gaps.py
verkkofillet/preprocessing/_find_gaps.py
verkkofillet/preprocessing/_find_intra_telo.py
verkkofillet/preprocessing/_find_inv_chr.py
verkkofillet/preprocessing/_getQV.py
verkkofillet/preprocessing/_highlight_nodes.py
verkkofillet/preprocessing/_read_chr.py
verkkofillet/preprocessing/_read_wirte.py
verkkofillet/preprocessing/_searchNodes.py
verkkofillet/tools/__init__.py
verkkofillet/tools/_asm_stats.py
verkkofillet/tools/_chrAssign.py
verkkofillet/tools/_detect_internal_telomere.py
verkkofillet/tools/_graphAlign.py
verkkofillet/tools/_insert_gap.py
verkkofillet/tools/_kmer.py
verkkofillet/tools/_modiFasta.py
verkkofillet/tools/_refAlign.py
verkkofillet/tools/_run_rm_rDNA.py
verkkofillet-0.1.4.dist-info/LICENSE
verkkofillet-0.1.4.dist-info/METADATA
verkkofillet-0.1.4.dist-info/WHEEL
verkkofillet-0.1.4.dist-info/top_level.txt
verkkofillet-0.1.4.dist-info/RECORD
