Metadata-Version: 2.2
Name: verkkofillet
Version: 0.1.4
Summary: verkko fillet pkg
Author-email: Juhyun Kim <kimj75@nih.gov>
Maintainer-email: Juhyun Kim <kimj75@nih.gov>
License: Copyright (c) 2018 The Python Packaging Authority
Project-URL: Homepage, https://github.com/jjuhyunkim/verkko-fillet
Project-URL: Issues, https://github.com/jjuhyunkim/verkko-fillet/issues
Classifier: Programming Language :: Python :: 3
Classifier: Operating System :: OS Independent
Requires-Python: >=3.9
License-File: LICENSE
